genes/__init__.py
genes/genalg/__init__.py
genes/genalg/api.py
genes/genalg/config.py
genes/genalg/factory.py
genes/genalg/factoryd/params.py
genes/genalg/operator_list.py
genes/genalg/stats.py
genes/genotype/__init__.py
genes/genotype/creature.py
genes/genotype/fitness_function.py
genes/genotype/genotype.py
genes/genotype/genotyped/error/genotype_factory_error.py
genes/genotype/genotyped/factory.py
genes/genotype/operator.py
genes/genotype/operatord/crossover.py
genes/genotype/operatord/mutation.py
genes/genotype/operatord/selection.py
genes/genotype/population.py
genes/genotype/populationd/factory.py
genes/stats/__init__.py
genes/stats/in_memory.py
genes-0.3.dist-info/WHEEL
genes-0.3.dist-info/METADATA
genes-0.3.dist-info/RECORD
